psswd_box_generator/__init__.py
psswd_box_generator/psswd_box_generator.py
psswd_box_generator-0.1.3.dist-info/METADATA
psswd_box_generator-0.1.3.dist-info/WHEEL
psswd_box_generator-0.1.3.dist-info/RECORD
