Metadata-Version: 2.1
Name: psswd-box-generator
Version: 0.1.3
Summary: Password generating library specifically built for use in my Psswd Box application.
Author: Melvin Quick
Author-email: melvinquick@proton.me
Requires-Python: >=3.12,<3.14
Classifier: Programming Language :: Python :: 3
Classifier: Programming Language :: Python :: 3.12
